anterior/__init__.py
anterior/source/__init__.py
anterior/source/frame.py
anterior/source/series.py
anterior/utils.py
anterior/warp/__init__.py
anterior/warp/backtester.py
anterior/warp/schedule.py
anterior-0.0.1.dist-info/LICENSE
anterior-0.0.1.dist-info/METADATA
anterior-0.0.1.dist-info/WHEEL
anterior-0.0.1.dist-info/RECORD
